pubcontrol_scopus/__init__.py
pubcontrol_scopus/config.py
pubcontrol_scopus/install.py
pubcontrol_scopus/main.py
pubcontrol_scopus/observe.py
pubcontrol_scopus/request.py
pubcontrol_scopus/templates/__init__.py
pubcontrol_scopus/templates/ini/__init__.py
pubcontrol_scopus/templates/ini/authors.j2
pubcontrol_scopus/templates/ini/config.j2
pubcontrol_scopus-0.0.0.18.dist-info/DESCRIPTION.rst
pubcontrol_scopus-0.0.0.18.dist-info/METADATA
pubcontrol_scopus-0.0.0.18.dist-info/RECORD
pubcontrol_scopus-0.0.0.18.dist-info/WHEEL
pubcontrol_scopus-0.0.0.18.dist-info/metadata.json
pubcontrol_scopus-0.0.0.18.dist-info/top_level.txt
